{
  "version": "v2",
  "motif_synonyms": {
    "animals": "animal",
    "bells": "bell",
    "birds": "bird",
    "bloom": "flower",
    "blossom": "flower",
    "boats": "boat",
    "bridges": "bridge",
    "buildings": "building",
    "butterflies": "butterfly",
    "candles": "candle",
    "castles": "castle",
    "cats": "cat",
    "caves": "cave",
    "chairs": "chair",
    "children": "child",
    "churches": "church building",
    "cities": "city",
    "clouds": "cloud",
    "crowns": "crown",
    "deserts": "desert",
    "dogs": "dog",
    "doors": "door",
    "eagles": "eagle",
    "elephants": "elephant",
    "fields": "field",
    "flowers": "flower",
    "forests": "forest",
    "fountains": "fountain",
    "gardens": "garden",
    "hills": "hill",
    "horses": "horse",
    "houses": "house",
    "islands": "island",
    "lakes": "lake",
    "lighthouses": "lighthouse",
    "lilies": "lily",
    "lions": "lion",
    "meadow": "field",
    "mirrors": "mirror",
    "moonlight": "moon",
    "mountains": "mountain",
    "ocean": "sea",
    "rainbows": "rainbow",
    "rivers": "river",
    "roads": "road",
    "roses": "rose",
    "ships": "ship",
    "skies": "sky",
    "snakes": "snake",
    "stars": "star",
    "storms": "storm",
    "sunlight": "sun",
    "sunrise": "sun",
    "sunset": "sun",
    "swords": "sword",
    "tables": "table",
    "temples": "temple",
    "towers": "tower",
    "trees": "tree",
    "vases": "vase",
    "volcanoes": "volcano",
    "water": "sea",
    "waterfalls": "waterfall",
    "waves": "sea",
    "whales": "whale",
    "windmills": "windmill",
    "windows": "window",
    "wolves": "wolf",
    "woods": "forest"
  },
  "motif_vocabulary": [
    "abbey",
    "abstraction",
    "acanthus",
    "accordion",
    "acorn",
    "acoustic horn",
    "acrobat",
    "actor",
    "actress",
    "admiral",
    "advertisement",
    "agriculture",
    "air force",
    "air transport",
    "airplane",
    "alchemy",
    "allegory",
    "alligator",
    "altar",
    "ambulance",
    "amphitheatre",
    "amulet",
    "amusement park",
    "anchor",
    "angel",
    "anger",
    "animal",
    "ankh",
    "anklet",
    "antelope",
    "apocalyptic literature",
    "apostle",
    "apple",
    "aqueduct",
    "arch",
    "archery",
    "architect",
    "architecture",
    "arm",
    "armed forces",
    "armor",
    "army",
    "arrow",
    "arrowhead",
    "art of drawing",
    "artificial pond",
    "artist",
    "astrology",
    "astronomer",
    "astronomy",
    "athlete",
    "autumn",
    "axe",
    "baboon",
    "bagpipe",
    "baker",
    "balcony",
    "ballet",
    "balloon",
    "bamboo",
    "banjo",
    "banner",
    "banquet",
    "baptismal font",
    "barn",
    "barrel",
    "baseball",
    "basket",
    "bat",
    "bathing",
    "bathroom",
    "battle",
    "beach",
    "bead",
    "bear",
    "bed",
    "bedroom",
    "bee",
    "bell",
    "bellows",
    "belt",
    "bench",
    "bicycle",
    "bird",
    "bishop",
    "blacksmith",
    "boat",
    "bobbin",
    "book",
    "boot",
    "botany",
    "bottle",
    "bow and arrow",
    "bowl",
    "box",
    "boxing",
    "boy",
    "bracelet",
    "bread",
    "breast badge",
    "breastfeeding",
    "bridge",
    "brooch",
    "bubble",
    "bucket",
    "buckle",
    "buffalo",
    "building",
    "bull",
    "burial",
    "bus",
    "butcher",
    "butterfly",
    "cabinet",
    "café",
    "cake",
    "calendar system",
    "calligraphy",
    "camel",
    "cameo",
    "camera",
    "camping",
    "canal",
    "candelabra",
    "candle",
    "candlestick",
    "cannon",
    "capital",
    "car",
    "caricature",
    "carriage",
    "carrot",
    "cart",
    "cartouche",
    "caryatid",
    "castanets",
    "castle",
    "cat",
    "cathedral",
    "cattle",
    "cauldron",
    "cave",
    "ceiling",
    "cello",
    "cemetery",
    "censer",
    "centaur",
    "ceremonial object",
    "ceremony",
    "chair",
    "chaise longue",
    "chalice",
    "chandelier",
    "chapel",
    "chariot",
    "cheese",
    "cheetah",
    "chemistry",
    "cherry",
    "chess",
    "chest",
    "chicken",
    "child",
    "childbirth",
    "chinoiserie",
    "church building",
    "church tabernacle",
    "cigarette",
    "circumcision",
    "circus",
    "city",
    "civil disorder",
    "clergy",
    "cloister",
    "clothes iron",
    "clothing",
    "cloud",
    "clown",
    "coat of arms",
    "coffee",
    "coffeepot",
    "coffin",
    "coin",
    "column",
    "commode",
    "common sunflower",
    "competitive swimming",
    "conceptual art",
    "concert",
    "cone",
    "container",
    "contemplation",
    "cornucopia",
    "corpse",
    "correspondence",
    "corset",
    "costume",
    "couch",
    "cougar",
    "couple",
    "courtyard",
    "crab",
    "crane",
    "crayfish",
    "crocodile",
    "crosier",
    "cross",
    "crowd",
    "crown",
    "crucifix",
    "crypt",
    "cue sports",
    "culinary equipment",
    "cult image",
    "cuneiform",
    "cup",
    "curtain",
    "cypress",
    "dagger",
    "daisy",
    "dance",
    "dancer",
    "dawn",
    "death",
    "deer",
    "deity",
    "demon",
    "demonstration",
    "department store",
    "desert",
    "desk",
    "devil",
    "diadem",
    "diary",
    "dice",
    "dining room",
    "dock",
    "document",
    "dog",
    "doll",
    "dolphin",
    "dome",
    "domestic worker",
    "domesticated turkey",
    "donkey",
    "door",
    "doorway",
    "double bass",
    "dove",
    "dragon",
    "dragonfly",
    "dress",
    "drinking",
    "drinking glass",
    "drinking vessel",
    "drum",
    "duck",
    "eagle",
    "ear",
    "earring",
    "earthquake",
    "easel",
    "eating",
    "economy",
    "education",
    "egg as food",
    "egg-and-dart",
    "eggplant",
    "elephant",
    "elm",
    "emblem",
    "emperor",
    "entertainment",
    "equestrianism",
    "evening",
    "everyday life",
    "ewer",
    "execution",
    "eye",
    "face",
    "factory",
    "fairy",
    "falcon",
    "family",
    "farm",
    "farmer",
    "fashion",
    "father",
    "faun",
    "fear",
    "feather",
    "fence",
    "fencing",
    "fibula",
    "field",
    "figure",
    "film",
    "fire",
    "firearm",
    "firefighter",
    "fireplace",
    "firework",
    "fish",
    "fishing",
    "flag",
    "flood",
    "flora",
    "flower",
    "flute",
    "fluting",
    "fog",
    "folding screen",
    "food",
    "foot",
    "footwear",
    "forest",
    "fortification",
    "fountain",
    "fox",
    "frog",
    "fruit",
    "funeral",
    "funerary art",
    "funerary structure",
    "furniture",
    "gadrooning",
    "gambling",
    "game",
    "garden",
    "gardener",
    "garland",
    "gas station",
    "gate",
    "general",
    "genre painting",
    "geometry",
    "gibbon",
    "giraffe",
    "girl",
    "gladiator",
    "globe",
    "glove",
    "gluttony",
    "goat",
    "goblet",
    "goddess",
    "golf",
    "goose",
    "gourd",
    "government",
    "graffiti",
    "grape",
    "griffin",
    "grotesque",
    "guard",
    "guitar",
    "hair",
    "hammer",
    "hammock",
    "hand",
    "hand fan",
    "handbag",
    "happiness",
    "harbor",
    "harp",
    "harpsichord",
    "harvest",
    "hat",
    "hawk",
    "haystack",
    "headdress",
    "headrest",
    "heart",
    "heaven",
    "hedgehog",
    "helicopter",
    "hell",
    "helmet",
    "hen",
    "herb",
    "hermaphrodite",
    "hieroglyph",
    "hill",
    "hilt",
    "hippocamp",
    "hippopotamus",
    "historical figure",
    "hookah",
    "horse",
    "hospital",
    "hot air balloon",
    "hotel",
    "hourglass",
    "house",
    "human anatomy",
    "human figure",
    "human head",
    "hunting",
    "hurricane",
    "ibex",
    "ice",
    "ice skating",
    "illness",
    "industrial sector",
    "infant",
    "infant bed",
    "inn",
    "innocence",
    "insect",
    "insignia",
    "interior",
    "island",
    "jackal",
    "jacket",
    "jaguar",
    "jar",
    "jewelry",
    "jinn",
    "jockey",
    "jug",
    "kettle",
    "key",
    "king",
    "kitchen",
    "kite",
    "knife",
    "knight",
    "ladder",
    "ladle",
    "lake",
    "lamb",
    "lamp",
    "landscape painting",
    "lantern",
    "law",
    "leaf",
    "leisure",
    "lemon",
    "leopard",
    "library",
    "light bulb",
    "lighthouse",
    "lighting",
    "lightning",
    "lily",
    "lion",
    "literature",
    "liturgical costume",
    "liturgical object",
    "livestock",
    "living room",
    "lizard",
    "lobster",
    "locket",
    "loom",
    "lotus",
    "love",
    "lower leg",
    "lute",
    "lyre",
    "machine",
    "magician",
    "mailbox",
    "maize",
    "man",
    "mandolin",
    "manuscript",
    "map",
    "marine art",
    "marine force",
    "market",
    "mask",
    "massacre",
    "mathematics",
    "medallion",
    "medicine",
    "menorah",
    "merchant",
    "mermaid",
    "merman",
    "microscope",
    "mihrab",
    "military",
    "military equipment",
    "military transport",
    "military uniform",
    "mirror",
    "mitre",
    "moat",
    "money",
    "monk",
    "monkey",
    "monster",
    "monument",
    "moon",
    "morning",
    "mosque",
    "mother",
    "motorcycle",
    "mountain",
    "mouse",
    "mouth",
    "mummy",
    "mural",
    "museum",
    "mushroom",
    "music",
    "musical instrument",
    "musical keyboard",
    "musician",
    "mythical creature",
    "mythology",
    "narcissus",
    "natural disaster",
    "nature",
    "navy",
    "necklace",
    "necktie",
    "needlework",
    "netsuke",
    "newspaper",
    "night",
    "nonrepresentational art",
    "nose jewellery",
    "nude",
    "nun",
    "nurse",
    "nymph",
    "oak",
    "obelisk",
    "onion",
    "opera",
    "orchid",
    "organ",
    "ornament",
    "owl",
    "oxen",
    "oyster",
    "pagoda",
    "painting",
    "palace",
    "palette",
    "palmette",
    "parable",
    "parasol",
    "park",
    "parrot",
    "party",
    "pastoral",
    "pavilion",
    "peace",
    "peach",
    "peafowl",
    "pear",
    "pelican",
    "pen",
    "pendant",
    "peony",
    "performance",
    "pheasant",
    "philosopher",
    "phoenix",
    "photography",
    "physical tool",
    "physician",
    "piano",
    "picnic",
    "pier",
    "pieuvre",
    "pigeon",
    "pilaster",
    "pineapple",
    "pipe",
    "pitcher",
    "planet",
    "plant",
    "plate",
    "playing",
    "playing card",
    "plough",
    "pocket watch",
    "poet",
    "poetry",
    "police",
    "politics",
    "pomegranate",
    "poppy",
    "portrait",
    "post office",
    "potato",
    "poverty",
    "prayer",
    "priest",
    "prince",
    "princess",
    "printing press",
    "prison",
    "prisoner",
    "processional parade",
    "profile",
    "prostitute",
    "public election",
    "punishment",
    "puppet",
    "putto",
    "pyramid",
    "queen",
    "rabbit",
    "railway",
    "railway station",
    "rain",
    "rainbow",
    "ram",
    "rapid transit",
    "rat",
    "rattle",
    "reading",
    "recreation",
    "reliquary",
    "reservoir",
    "restaurant",
    "rhinoceros",
    "ring",
    "river",
    "road",
    "robe",
    "rock",
    "roof",
    "rooster",
    "rosary",
    "rose",
    "ruins",
    "running",
    "sadness",
    "sailing",
    "sailor",
    "saint",
    "salamander",
    "samurai",
    "sarcophagus",
    "satire",
    "satyr",
    "saucer",
    "scarab",
    "scarf",
    "school",
    "science",
    "scientist",
    "scissors",
    "scorpion",
    "scroll",
    "sculpture",
    "sea",
    "seahorse",
    "seal",
    "seashell",
    "season",
    "self-portrait",
    "sewing",
    "shack",
    "sheep",
    "shepherd",
    "shield",
    "ship",
    "shipwreck",
    "shirt",
    "shoe",
    "shop",
    "shuttlecock",
    "sibyl",
    "sideboard",
    "sign",
    "singer",
    "singing",
    "siren",
    "skeleton",
    "skiing",
    "skull",
    "sky",
    "slave",
    "slavery",
    "sled",
    "sleep",
    "smoking",
    "snail",
    "snake",
    "snow",
    "soldier",
    "spear",
    "spectator",
    "sphinx",
    "spider",
    "spindle",
    "spinning wheel",
    "spoon",
    "sport",
    "spring",
    "squid",
    "squirrel",
    "stable",
    "stadium",
    "stage design",
    "stage magic",
    "stairs",
    "star",
    "still life",
    "stool",
    "storm",
    "strawberry",
    "stream",
    "street",
    "street scene",
    "student",
    "stupa",
    "suffering",
    "suit",
    "summer",
    "sun",
    "sundial",
    "swan",
    "sword",
    "synagogue",
    "table",
    "tablet",
    "tankard",
    "tavern",
    "taxi",
    "tea",
    "tea caddy",
    "tea ceremony",
    "tea house",
    "teacher",
    "teapot",
    "telephone",
    "telescope",
    "television",
    "temple",
    "tennis",
    "tent",
    "textile",
    "theatre art",
    "throne",
    "tiger",
    "timepiece",
    "tomato",
    "tomb",
    "tombstone",
    "tower",
    "town",
    "toy",
    "tractor",
    "trailer",
    "train",
    "tram",
    "transatlantic telegraph cable",
    "transport",
    "tray",
    "tree",
    "tricorne",
    "trombone",
    "trompe-l'œil",
    "trophy",
    "truck",
    "trumpet",
    "tulip",
    "tunnel",
    "tureen",
    "turtle",
    "typewriter",
    "umbrella",
    "unicorn",
    "uniform",
    "urn",
    "vase",
    "vegetable",
    "village",
    "vine",
    "viola",
    "viola flower",
    "violin",
    "volcano",
    "wagon",
    "walking",
    "war",
    "warehouse",
    "warrior",
    "wash basin",
    "washing",
    "water lily",
    "water well",
    "waterfall",
    "watermill",
    "weapon",
    "wedding",
    "weft-knit fabric",
    "weighing scale",
    "whale",
    "wig",
    "wind",
    "wind wave",
    "windmill",
    "window",
    "wine",
    "winter",
    "witch",
    "wolf",
    "woman",
    "work",
    "wreath",
    "wrestling",
    "writing",
    "writing implement",
    "zebra",
    "zodiac"
  ],
  "mood_synonyms": {
    "peaceful": "calm",
    "serene": "calm",
    "tranquil": "calm",
    "quiet": "calm",
    "gentle": "calm",
    "cozy": "warm",
    "inviting": "warm",
    "comforting": "warm",
    "cheerful": "joyful",
    "happy": "joyful",
    "bright": "joyful",
    "sad": "melancholic",
    "sorrowful": "melancholic",
    "lonely": "melancholic",
    "gloomy": "dark",
    "somber": "dark",
    "eerie": "dark",
    "haunting": "mysterious",
    "enigmatic": "mysterious",
    "dramatic": "dramatic",
    "intense": "dramatic",
    "powerful": "dramatic",
    "lively": "vibrant",
    "energetic": "vibrant",
    "dynamic": "vibrant",
    "delicate": "ethereal",
    "dreamy": "ethereal",
    "airy": "ethereal",
    "romantic": "romantic",
    "passionate": "romantic",
    "nostalgic": "nostalgic",
    "retro": "nostalgic",
    "solemn": "solemn",
    "sacred": "solemn",
    "grand": "majestic",
    "magnificent": "majestic",
    "sublime": "majestic",
    "playful": "playful",
    "whimsical": "playful",
    "minimalist": "minimal",
    "simple": "minimal",
    "sparse": "minimal"
  },
  "mood_vocabulary": [
    "calm",
    "warm",
    "joyful",
    "melancholic",
    "dark",
    "mysterious",
    "dramatic",
    "vibrant",
    "ethereal",
    "romantic",
    "nostalgic",
    "solemn",
    "majestic",
    "playful",
    "minimal",
    "fresh",
    "cool",
    "elegant",
    "raw",
    "tender"
  ],
  "style_synonyms": {
    "abstract art": "abstract",
    "abstraction": "abstract",
    "impressionistic": "impressionism",
    "realistic": "realism",
    "photorealistic": "realism",
    "surreal": "surrealism",
    "surrealistic": "surrealism",
    "expressionistic": "expressionism",
    "pop art": "pop",
    "minimalist": "minimalism",
    "art nouveau": "art_nouveau",
    "art deco": "art_deco",
    "watercolour": "watercolor",
    "oil painting": "oil",
    "digital art": "digital",
    "illustration": "illustration",
    "sketch": "sketch",
    "photography": "photography",
    "collage": "collage",
    "mixed media": "mixed_media"
  },
  "style_vocabulary": [
    "abstract",
    "impressionism",
    "realism",
    "surrealism",
    "expressionism",
    "pop",
    "minimalism",
    "art_nouveau",
    "art_deco",
    "watercolor",
    "oil",
    "digital",
    "illustration",
    "sketch",
    "photography",
    "collage",
    "mixed_media",
    "cubism",
    "baroque",
    "contemporary"
  ],
  "subject_synonyms": {
    "scenery": "landscape",
    "nature": "landscape",
    "countryside": "landscape",
    "seascape": "marine",
    "sea view": "marine",
    "face": "portrait",
    "self-portrait": "portrait",
    "figure study": "portrait",
    "flowers": "still_life",
    "objects": "still_life",
    "arrangement": "still_life",
    "city": "urban",
    "cityscape": "urban",
    "street": "urban",
    "building": "architecture",
    "interior": "architecture",
    "animal": "animal",
    "wildlife": "animal",
    "mythology": "mythological",
    "religious": "religious",
    "historical": "historical"
  },
  "subject_vocabulary": [
    "landscape",
    "marine",
    "portrait",
    "still_life",
    "urban",
    "architecture",
    "animal",
    "mythological",
    "religious",
    "historical",
    "figurative",
    "botanical",
    "abstract",
    "genre",
    "nude"
  ],
  "stopwords": [
    "background",
    "foreground",
    "object",
    "thing",
    "stuff",
    "element",
    "detail",
    "part",
    "area",
    "section",
    "piece",
    "image",
    "picture",
    "painting",
    "artwork",
    "art",
    "scene",
    "view",
    "composition",
    "color",
    "colour",
    "tone",
    "shade",
    "texture",
    "pattern",
    "style",
    "technique",
    "medium",
    "various",
    "multiple",
    "several",
    "many",
    "some",
    "other",
    "etc",
    "and",
    "or",
    "the",
    "a",
    "an"
  ]
}
